neroRL/__init__.py
neroRL/enjoy.py
neroRL/eval.py
neroRL/eval_checkpoints.py
neroRL/evaluator.py
neroRL/train.py
neroRL/tune.py
neroRL/environments/__init__.py
neroRL/environments/ballet_wrapper.py
neroRL/environments/cartpole_wrapper.py
neroRL/environments/env.py
neroRL/environments/minigrid_vec_wrapper.py
neroRL/environments/minigrid_wrapper.py
neroRL/environments/mortar_minigrid.py
neroRL/environments/obstacle_tower_env.py
neroRL/environments/obstacle_tower_wrapper.py
neroRL/environments/procgen_wrapper.py
neroRL/environments/unity_wrapper.py
neroRL/environments/wrapper.py
neroRL/environments/ballet/__init__.py
neroRL/environments/ballet/ballet_environment.py
neroRL/environments/ballet/ballet_environment_core.py
neroRL/environments/ballet/ballet_environment_test.py
neroRL/environments/wrappers/__init__.py
neroRL/environments/wrappers/frame_skip.py
neroRL/environments/wrappers/grayscale_visual_observation.py
neroRL/environments/wrappers/last_action_to_obs.py
neroRL/environments/wrappers/last_reward_to_obs.py
neroRL/environments/wrappers/pytorch_shape.py
neroRL/environments/wrappers/scaled_visual_observation.py
neroRL/environments/wrappers/stacked_observation.py
neroRL/nn/__init__.py
neroRL/nn/actor_critic.py
neroRL/nn/base.py
neroRL/nn/body.py
neroRL/nn/encoder.py
neroRL/nn/heads.py
neroRL/nn/module.py
neroRL/nn/recurrent.py
neroRL/sampler/__init__.py
neroRL/sampler/buffer.py
neroRL/sampler/episode_sampler.py
neroRL/sampler/trajectory_sampler.py
neroRL/trainers/__init__.py
neroRL/trainers/policy_gradient/__init__.py
neroRL/trainers/policy_gradient/base.py
neroRL/trainers/policy_gradient/ppo_decoupled.py
neroRL/trainers/policy_gradient/ppo_shared.py
neroRL/utils/__init__.py
neroRL/utils/decay_schedules.py
neroRL/utils/grid_search.py
neroRL/utils/monitor.py
neroRL/utils/utils.py
neroRL/utils/video_recorder.py
neroRL/utils/worker.py
neroRL/utils/yaml_parser.py
neroRL-0.0.4.dist-info/LICENSE
neroRL-0.0.4.dist-info/METADATA
neroRL-0.0.4.dist-info/WHEEL
neroRL-0.0.4.dist-info/entry_points.txt
neroRL-0.0.4.dist-info/top_level.txt
neroRL-0.0.4.dist-info/RECORD
