Metadata-Version: 2.1
Name: neroRL
Version: 0.0.4
Summary: A library for Deep Reinforcement Learning (PPO) in PyTorch
Home-page: https://github.com/MarcoMeter/neroRL
License: UNKNOWN
Project-URL: Github, https://github.com/MarcoMeter/neroRL
Project-URL: Bug Tracker, https://github.com/MarcoMeter/neroRL/issues
Keywords: Deep Reinforcement Learning,PyTorch,Proximal Policy Optimization,PPO,Recurrent,Recurrence,LSTM,GRU
Platform: UNKNOWN
Classifier: Programming Language :: Python :: 3
Classifier: License :: OSI Approved :: MIT License
Classifier: Operating System :: OS Independent
Requires-Python: >=3.6
License-File: LICENSE
Requires-Dist: dm-env (==1.5)
Requires-Dist: docopt
Requires-Dist: gym
Requires-Dist: gym-minigrid (==1.0.2)
Requires-Dist: jinja2
Requires-Dist: matplotlib
Requires-Dist: opencv-python
Requires-Dist: pandas
Requires-Dist: procgen
Requires-Dist: pycolab (==1.2)
Requires-Dist: pygame
Requires-Dist: pyglet
Requires-Dist: ruamel.yaml
Requires-Dist: scipy
Requires-Dist: windows-curses ; sys_platform == "win32"
